sTTcv.py
sttcv-1.0.0.dist-info/WHEEL
sttcv-1.0.0.dist-info/METADATA
sttcv-1.0.0.dist-info/RECORD
